simple_math_pip/__init__.py
simple_math_pip/number.py
simple_math_pip/operations.py
simple_math_pip-0.1.0.dist-info/METADATA
simple_math_pip-0.1.0.dist-info/WHEEL
simple_math_pip-0.1.0.dist-info/RECORD
